alphawaves/__init__.py
alphawaves/dataset.py
alphawaves/download.py
alphawaves-0.5.dist-info/LICENSE
alphawaves-0.5.dist-info/METADATA
alphawaves-0.5.dist-info/WHEEL
alphawaves-0.5.dist-info/top_level.txt
alphawaves-0.5.dist-info/RECORD
