Metadata-Version: 2.1
Name: alphawaves
Version: 0.5
Summary: Alpha Waves Dataset
Home-page: https://github.com/plcrodrigues/Alpha-Waves-Dataset
Author: Pedro Rodrigues
Author-email: pedro.rodrigues01@gmail.com
License: new BSD
Keywords: EEG neuroscience signal processing
Classifier: Development Status :: 3 - Alpha
Classifier: Intended Audience :: Science/Research
Classifier: Topic :: Scientific/Engineering
Classifier: License :: OSI Approved
Classifier: Programming Language :: Python :: 3.9
Classifier: Programming Language :: Python :: 3.10
License-File: LICENSE
Requires-Dist: mne (==0.24.1)
Requires-Dist: pyriemann (>=0.2.6)
Requires-Dist: scipy (>=1.8)
Requires-Dist: scikit-learn (>=0.23)
Requires-Dist: matplotlib (>=3.4.3)
Requires-Dist: pooch (==1.8.0)
